vbt_yaml/__init__.py
vbt_yaml/__main__.py
vbt_yaml/create_yaml.py
vbt_yaml-0.0.5.dist-info/METADATA
vbt_yaml-0.0.5.dist-info/WHEEL
vbt_yaml-0.0.5.dist-info/top_level.txt
vbt_yaml-0.0.5.dist-info/RECORD
